{"list":[
    {"state":"상태","date":"일정","wdate":"작업일","mod":"수정","pub":"퍼블","pln":"기획","des":"디자인","dev":"개발","type":"유형","name":"파일명","id":"화면ID","d1":"D1","d2":"D2","d3":"D3","d4":"D4","d5":"D5","root":"root","memo":"메모"},
    {"state":"완료","date":"20230224","wdate":"null","mod":"","pub":"권오택","pln":"이주영","des":"000100","dev":"000100","type":"M","name":"KOM01010000M","id":"KOM01010000M","d1":"메인","d2":"(MO)","d3":"","d4":"","d5":"","root":"/kosef/moWeb/main/","memo":""},
    {"state":"완료","date":"20230224","wdate":"null","mod":"","pub":"권오택","pln":"이주영","des":"000100","dev":"000100","type":"P","name":"KOM01020100P","id":"KOM01020100P","d1":"[팝업]키자미디어_[탭]키자매거진","d2":"(MO)","d3":"","d4":"","d5":"","root":"/kosef/moWeb/main/","memo":"메인페이지확인"},
    {"state":"완료","date":"20230224","wdate":"null","mod":"","pub":"권오택","pln":"이주영","des":"000100","dev":"000100","type":"P","name":"KOM01020200P","id":"KOM01020200P","d1":"[팝업]키자미디어_[탭]키자TV","d2":"(MO)","d3":"","d4":"","d5":"","root":"/kosef/moWeb/main/","memo":"메인페이지확인"},
    {"state":"완료","date":"20230224","wdate":"null","mod":"","pub":"권오택","pln":"이주영","des":"000100","dev":"000100","type":"P","name":"KOM01030300P","id":"KOM01030300P","d1":"메인","d2":"[팝업]투자가이드","d3":"","d4":"","d5":"","root":"/kosef/moWeb/main/","memo":"메인페이지확인"},
    {"state":"완료","date":"20230224","wdate":"null","mod":"","pub":"권오택","pln":"이주영","des":"000100","dev":"000100","type":"P","name":"KOM01040400P","id":"KOM01040400P","d1":"메인","d2":"[팝업]KOSEF","d3":"","d4":"","d5":"","root":"/kosef/moWeb/main/","memo":"메인페이지확인"},
    {"state":"완료","date":"20230224","wdate":"null","mod":"","pub":"권오택","pln":"이주영","des":"000100","dev":"000100","type":"M","name":"KOM01020000P","id":"KOM01020000P","d1":"메인","d2":"[팝업]전체메뉴","d3":"","d4":"","d5":"","root":"/kosef/moWeb/main/","memo":"메인페이지확인"},
    {"state":"완료","date":"20230224","wdate":"null","mod":"","pub":"권오택","pln":"이주영","des":"000100","dev":"000100","type":"P","name":"modal","id":"modal","d1":"메인","d2":"[팝업]통합검색","d3":"","d4":"","d5":"","root":"/kosef/moWeb/html/","memo":"KOM01030000P"},
    {"state":"완료","date":"20230224","wdate":"null","mod":"","pub":"권오택","pln":"이주영","des":"000100","dev":"000100","type":"P","name":"modal","id":"modal","d1":"메인","d2":"[팝업]개인정보처리방침","d3":"","d4":"","d5":"","root":"/kosef/moWeb/html/","memo":"KIM0106000000P"},
    {"state":"완료","date":"20230224","wdate":"null","mod":"","pub":"권오택","pln":"이주영","des":"000100","dev":"000100","type":"P","name":"modal","id":"modal","d1":"메인","d2":"[팝업]이메일무단수집금지","d3":"","d4":"","d5":"","root":"/kosef/moWeb/html/","memo":"KIM0108000000P"},
    {"state":"완료","date":"20230224","wdate":"null","mod":"","pub":"권오택","pln":"이주영","des":"000100","dev":"000100","type":"P","name":"modal","id":"modal","d1":"메인","d2":"[팝업]메인공지","d3":"","d4":"","d5":"","root":"/kosef/moWeb/html/","memo":"KIM0701000000P"},
    {"state":"완료","date":"20230207","wdate":"null","mod":"","pub":"권오택","pln":"이주영","des":"000100","dev":"000100","type":"P","name":"KOM01040000M","id":"KOM01040000M","d1":"메인","d2":"통합검색 결과","d3":"","d4":"","d5":"","root":"/kosef/moWeb/search/","memo":""},
    {"state":"제외","date":"20230215","wdate":"null","mod":"","pub":"권오택","pln":"이주영","des":"000100","dev":"000100","type":"M","name":"KOM01040000M","id":"KOM01040000M","d1":"메인","d2":"통합검색 결과","d3":"","d4":"","d5":"","root":"/kosef/moWeb/search/","memo":""},
    {"state":"제외","date":"20230215","wdate":"null","mod":"","pub":"권오택","pln":"이주영","des":"000100","dev":"000100","type":"M","name":"KOM01050000P","id":"KOM01050000P","d1":"메인","d2":"사이트맵","d3":"","d4":"","d5":"","root":"/kosef/moWeb/product/","memo":""},
    {"state":"제외","date":"20230215","wdate":"null","mod":"","pub":"권오택","pln":"이주영","des":"000100","dev":"000100","type":"P","name":"KOM01060000P","id":"KOM01060000P","d1":"메인","d2":"[팝업]실시간 지수정보","d3":"","d4":"","d5":"","root":"/kosef/moWeb/product/","memo":""},
    {"state":"완료","date":"20230215","wdate":"20230127","mod":"","pub":"권오택","pln":"이주영","des":"000100","dev":"000100","type":"M","name":"KOM02010100M","id":"KOM02010100M","d1":"상품정보","d2":"키움ETF","d3":"목록","d4":"","d5":"","root":"/kosef/moWeb/product/","memo":""},
    {"state":"제외","date":"20230215","wdate":"null","mod":"","pub":"권오택","pln":"이주영","des":"000100","dev":"000100","type":"P","name":"KOM02010101P","id":"KOM02010101P","d1":"상품정보","d2":"키움ETF","d3":"목록","d4":"[팝업]펀드비교 ","d5":"","root":"/kosef/moWeb/product/","memo":""},
    {"state":"제외","date":"20230215","wdate":"null","mod":"","pub":"권오택","pln":"이주영","des":"000100","dev":"000100","type":"P","name":"KOM02010102P","id":"KOM02010102P","d1":"상품정보","d2":"키움ETF","d3":"목록","d4":"[팝업]펀드비교 결과","d5":"","root":"/kosef/moWeb/product/","memo":""},
    {"state":"완료","date":"20230215","wdate":"20230127","mod":"","pub":"고광수","pln":"이주영","des":"000100","dev":"000100","type":"P","name":"KOM02010200M","id":"KOM02010200M","d1":"상품정보","d2":"키움ETF","d3":"상세","d4":"","d5":"","root":"/kosef/moWeb/product/","memo":""},
    {"state":"제외","date":"20230215","wdate":"null","mod":"","pub":"권오택","pln":"이주영","des":"000100","dev":"000100","type":"M","name":"KOM02020000M","id":"KOM02020000M","d1":"상품정보","d2":"수익률 계산기","d3":"","d4":"","d5":"","root":"/kosef/moWeb/product/","memo":""},
    {"state":"완료","date":"20230127","wdate":"20230130","mod":"","pub":"권오택","pln":"이주영","des":"000100","dev":"000100","type":"M","name":"KOM03010000M","id":"KOM03010000M","d1":"","d2":"상품REPORT","d3":"","d4":"","d5":"","root":"/kosef/moWeb/product/","memo":""},
    {"state":"완료","date":"20230127","wdate":"20230130","mod":"","pub":"고광수","pln":"이주영","des":"000100","dev":"000100","type":"P","name":"KOM03020000M","id":"KOM03020000M","d1":"ETF 자료실","d2":"상품별 관련 자료","d3":"","d4":"","d5":"","root":"/kosef/moWeb/product/","memo":""},
    {"state":"완료","date":"20230127","wdate":"20230130","mod":"","pub":"고광수","pln":"이주영","des":"000100","dev":"000100","type":"P","name":"modal","id":"modal","d1":"ETF 자료실","d2":"상품별 관련 자료","d3":"[팝업]신탁계약서/투자설명서","d4":"","d5":"","root":"/kosef/moWeb/html/","memo":""},
    {"state":"완료","date":"20230127","wdate":"20230130","mod":"","pub":"고광수","pln":"이주영","des":"000100","dev":"000100","type":"P","name":"modal","id":"modal","d1":"ETF 자료실","d2":"상품별 관련 자료","d3":"[팝업]분배금지급현황","d4":"","d5":"","root":"/kosef/moWeb/html/","memo":""},
    {"state":"완료","date":"20230127","wdate":"20230130","mod":"","pub":"고광수","pln":"이주영","des":"000100","dev":"000100","type":"P","name":"modal","id":"modal","d1":"ETF 자료실","d2":"상품별 관련 자료","d3":"[팝업]PDF 현황","d4":"","d5":"","root":"/kosef/moWeb/html/","memo":""},
    {"state":"완료","date":"20230201","wdate":"","mod":"","pub":"권오택","pln":"이주영","des":"000100","dev":"000100","type":"T","name":"KOM04010100M","id":"KOM04010100M","d1":"투자정보","d2":"ETF 펀드뉴스","d3":"목록","d4":"","d5":"","root":"/kosef/moWeb/invest/","memo":""},
    {"state":"완료","date":"20230201","wdate":"null","mod":"","pub":"고광수","pln":"이주영","des":"000100","dev":"000100","type":"T","name":"KOM04020101T","id":"KOM04020101T","d1":"투자정보","d2":"키움매거진&TV","d3":"[탭]키움매거진","d4":"목록","d5":"","root":"/kosef/moWeb/invest/","memo":""},
    {"state":"완료","date":"20230201","wdate":"null","mod":"","pub":"고광수","pln":"이주영","des":"000100","dev":"000100","type":"T","name":"KOM04020102T","id":"KOM04020102T","d1":"투자정보","d2":"키움매거진&TV","d3":"[탭]키움매거진","d4":"[팝업]키움매거진 상세","d5":"","root":"/kosef/moWeb/invest/","memo":""},
    {"state":"완료","date":"20230206","wdate":"null","mod":"","pub":"고광수","pln":"이주영","des":"000100","dev":"000100","type":"T","name":"KOM04020201T","id":"KOM04020201T","d1":"투자정보","d2":"키움매거진&TV","d3":"[탭]키자TV","d4":"목록","d5":"","root":"/kosef/moWeb/invest/","memo":""},
    {"state":"완료","date":"20230206","wdate":"null","mod":"","pub":"고광수","pln":"이주영","des":"000100","dev":"000100","type":"P","name":"modal","id":"modal","d1":"투자정보","d2":"키움매거진&TV","d3":"[탭]키자TV","d4":"[팝업]키자TV 상세","d5":"","root":"/kosef/moWeb/html/","memo":""},
    {"state":"완료","date":"20230227","wdate":"null","mod":"","pub":"권오택","pln":"이주영","des":"000100","dev":"000100","type":"T","name":"KOM04030000T","id":"KOM04030000T","d1":"투자정보","d2":"ETF 투자가이드","d3":"[탭]투자방법","d4":"","d5":"","root":"/kosef/moWeb/invest/","memo":""},
    {"state":"제외","date":"20230215","wdate":"null","mod":"","pub":"권오택","pln":"이주영","des":"000100","dev":"000100","type":"T","name":"KOM04030200T","id":"KOM04030200T","d1":"투자정보","d2":"ETF 투자가이드","d3":"[탭]투자방법 비교","d4":"","d5":"","root":"/kosef/moWeb/product/","memo":""},
    {"state":"제외","date":"20230215","wdate":"null","mod":"","pub":"권오택","pln":"이주영","des":"000100","dev":"000100","type":"T","name":"KOM04030300T","id":"KOM04030300T","d1":"투자정보","d2":"ETF 투자가이드","d3":"[탭]판매처","d4":"","d5":"","root":"/kosef/moWeb/product/","memo":""},
    {"state":"완료","date":"20230206","wdate":"null","mod":"","pub":"권오택","pln":"이주영","des":"000100","dev":"000100","type":"M","name":"KOM05010100M","id":"KOM05010100M","d1":"공시/공지","d2":"공시정보","d3":"목록","d4":"","d5":"","root":"/kosef/moWeb/notice/","memo":""},
    {"state":"완료","date":"20230206","wdate":"null","mod":"","pub":"권오택","pln":"이주영","des":"000100","dev":"000100","type":"M","name":"KOM05010200M","id":"KOM05010200M","d1":"공시/공지","d2":"공시정보","d3":"상세","d4":"","d5":"","root":"/kosef/moWeb/notice/","memo":""},
    {"state":"완료","date":"20230209","wdate":"null","mod":"","pub":"권오택","pln":"이주영","des":"000100","dev":"000100","type":"T","name":"KOM05020101T","id":"KOM05020101T","d1":"공시/공지","d2":"공지사항","d3":"공지/이벤트","d4":"[탭]공지사항","d5":"목록","root":"/kosef/moWeb/notice/","memo":""},
    {"state":"완료","date":"20230213","wdate":"null","mod":"","pub":"권오택","pln":"이주영","des":"000100","dev":"000100","type":"T","name":"KOM05020102T","id":"KOM05020102T","d1":"공시/공지","d2":"공지사항","d3":"공지/이벤트","d4":"[탭]공지사항","d5":"상세","root":"/kosef/moWeb/notice/","memo":""},
    {"state":"완료","date":"20230213","wdate":"null","mod":"","pub":"권오택","pln":"이주영","des":"000100","dev":"000100","type":"T","name":"KOM05020201T","id":"KOM05020201T","d1":"공시/공지","d2":"공지사항","d3":"공지/이벤트","d4":"[탭]이벤트","d5":"목록","root":"/kosef/moWeb/notice/","memo":""},
    {"state":"완료","date":"20230213","wdate":"null","mod":"","pub":"권오택","pln":"이주영","des":"000100","dev":"000100","type":"T","name":"KOM05020202T","id":"KOM05020202T","d1":"공시/공지","d2":"공지사항","d3":"공지/이벤트","d4":"[탭]이벤트","d5":"상세","root":"/kosef/moWeb/notice/","memo":""},
    {"state":"완료","date":"20230213","wdate":"null","mod":"","pub":"권오택","pln":"이주영","des":"000100","dev":"000100","type":"M","name":"KOM05030000M","id":"KOM05030000M","d1":"공시/공지","d2":"공지사항","d3":"FAQ","d4":"","d5":"","root":"/kosef/moWeb/notice/","memo":""},
    {"state":"완료","date":"20230213","wdate":"null","mod":"","pub":"권오택","pln":"이주영","des":"000100","dev":"000100","type":"M","name":"KOM05040000M","id":"KOM05040000M","d1":"공시/공지","d2":"About KOSEF&히어로즈","d3":"","d4":"","d5":"","root":"/kosef/moWeb/notice/","memo":""},
    {"state":"완료","date":"20230227","wdate":"null","mod":"","pub":"권오택","pln":"이주영","des":"000100","dev":"000100","type":"M","name":"KOM06000000M","id":"KOM06000000M","d1":"ENGLISH","d2":"","d3":"","d4":"","d5":"","root":"/kosef/moWeb/eng/","memo":""}
    ]}
    
    